[
  {
    "slug": "coding",
    "label": "Coding",
    "count": 38,
    "latestDate": "2026-04-09"
  },
  {
    "slug": "agents",
    "label": "AI Assistants",
    "count": 34,
    "latestDate": "2026-04-09"
  },
  {
    "slug": "research",
    "label": "Research",
    "count": 25,
    "latestDate": "2026-04-09"
  },
  {
    "slug": "fine-tuning",
    "label": "Custom AI",
    "count": 18,
    "latestDate": "2026-04-09"
  },
  {
    "slug": "china-models",
    "label": "Chinese AI",
    "count": 15,
    "latestDate": "2026-04-09"
  },
  {
    "slug": "multimodal",
    "label": "Images, Audio & Video",
    "count": 13,
    "latestDate": "2026-04-09"
  },
  {
    "slug": "enterprise",
    "label": "Business AI",
    "count": 10,
    "latestDate": "2026-04-09"
  },
  {
    "slug": "open-source",
    "label": "Open Source",
    "count": 10,
    "latestDate": "2026-04-09"
  },
  {
    "slug": "voice",
    "label": "Voice",
    "count": 9,
    "latestDate": "2026-04-09"
  },
  {
    "slug": "safety",
    "label": "AI Safety",
    "count": 7,
    "latestDate": "2026-04-09"
  },
  {
    "slug": "benchmarks",
    "label": "AI Testing",
    "count": 7,
    "latestDate": "2026-04-09"
  },
  {
    "slug": "computer-use",
    "label": "AI Using Computers",
    "count": 7,
    "latestDate": "2026-04-09"
  },
  {
    "slug": "tool-use",
    "label": "AI Using Tools",
    "count": 7,
    "latestDate": "2026-04-09"
  },
  {
    "slug": "reasoning",
    "label": "AI Thinking",
    "count": 4,
    "latestDate": "2026-04-09"
  },
  {
    "slug": "inference",
    "label": "Speed & Cost",
    "count": 4,
    "latestDate": "2026-04-09"
  }
]
