[
  {
    "slug": "agents",
    "label": "AI Assistants",
    "count": 20,
    "latestDate": "2026-04-07"
  },
  {
    "slug": "coding",
    "label": "Coding",
    "count": 17,
    "latestDate": "2026-04-07"
  },
  {
    "slug": "research",
    "label": "Research",
    "count": 12,
    "latestDate": "2026-04-07"
  },
  {
    "slug": "fine-tuning",
    "label": "Custom AI",
    "count": 11,
    "latestDate": "2026-04-07"
  },
  {
    "slug": "china-models",
    "label": "Chinese AI",
    "count": 10,
    "latestDate": "2026-04-07"
  },
  {
    "slug": "tool-use",
    "label": "AI Using Tools",
    "count": 6,
    "latestDate": "2026-04-07"
  },
  {
    "slug": "enterprise",
    "label": "Business AI",
    "count": 6,
    "latestDate": "2026-04-07"
  },
  {
    "slug": "safety",
    "label": "AI Safety",
    "count": 5,
    "latestDate": "2026-04-07"
  },
  {
    "slug": "open-source",
    "label": "Open Source",
    "count": 5,
    "latestDate": "2026-04-07"
  },
  {
    "slug": "computer-use",
    "label": "AI Using Computers",
    "count": 4,
    "latestDate": "2026-04-07"
  },
  {
    "slug": "multimodal",
    "label": "Images, Audio & Video",
    "count": 4,
    "latestDate": "2026-04-07"
  },
  {
    "slug": "voice",
    "label": "Voice",
    "count": 4,
    "latestDate": "2026-04-07"
  },
  {
    "slug": "benchmarks",
    "label": "AI Testing",
    "count": 2,
    "latestDate": "2026-04-07"
  },
  {
    "slug": "reasoning",
    "label": "AI Thinking",
    "count": 2,
    "latestDate": "2026-04-07"
  },
  {
    "slug": "inference",
    "label": "Speed & Cost",
    "count": 1,
    "latestDate": "2026-04-07"
  }
]
