{
  "generatedAt": "2026-04-19T00:42:50.454Z",
  "handle": "GoogleLabs",
  "name": "Google Labs",
  "itemCount": 1,
  "latestDate": "2026-04-19",
  "items": [
    {
      "id": "8c8b3e0f6751607d",
      "date": "2026-04-19",
      "sourceType": "x",
      "sourceGroup": "mirrored",
      "sourceName": "X",
      "sourceKey": "x:GoogleLabs",
      "builderOrOrg": "Google Labs",
      "title": "We’ve watched you create the impossible with @FlowbyGoogle… today, the Flow family is growing.…",
      "url": "https://x.com/GoogleLabs/status/2045250788864495874",
      "publishedAt": "2026-04-17T21:19:21.000Z",
      "content": "We’ve watched you create the impossible with @FlowbyGoogle… today, the Flow family is growing. 🚀 Meet @googleflowmusic (formerly ProducerAI) - a standalone site that helps you create, share, and remix original music. Using natural language prompts, you can turn your imagination into fully produced tracks. 🌊 Flow = Images & Videos 🎵 Flow Music = Songs & Playlists",
      "summary": "We’ve watched you create the impossible with @FlowbyGoogle… today, the Flow family is growing. 🚀 Meet @googleflowmusic (formerly ProducerAI) - a standalone site that helps you create, share, and remix original music. U…",
      "regionTags": [],
      "metrics": {
        "likes": 1204,
        "retweets": 150,
        "replies": 40
      },
      "topics": [
        {
          "slug": "multimodal",
          "label": "Images, Audio & Video",
          "confidence": 0.69,
          "rationale": [
            "image",
            "video"
          ],
          "score": 2
        },
        {
          "slug": "fine-tuning",
          "label": "Custom AI",
          "confidence": 0.5700000000000001,
          "rationale": [
            "rl"
          ],
          "score": 1
        }
      ],
      "section": "Builders",
      "importanceScore": 0.7,
      "noveltyScore": 1,
      "previouslySelected": false,
      "digestScore": 0.8,
      "whyThisMatters": ""
    }
  ]
}
